dotsy/__init__.py
dotsy/dicy.py
dotsy/ency.py
dotsy-0.2.0.dist-info/LICENSE
dotsy-0.2.0.dist-info/METADATA
dotsy-0.2.0.dist-info/WHEEL
dotsy-0.2.0.dist-info/top_level.txt
dotsy-0.2.0.dist-info/RECORD
