Metadata-Version: 2.1
Name: dotsy
Version: 0.2.0
Summary: dot-accessible dictionaries (dicy) and dictionary-containing encyclopedia classes (ency)
Home-page: https://github.com/lcdavis13/dotsy
Author: Levi Davis
Author-email: levi.davis.co@gmail.com
Classifier: Programming Language :: Python :: 3
Classifier: License :: OSI Approved :: MIT License
Classifier: Operating System :: OS Independent
Requires-Python: >=3.6
License-File: LICENSE
